muffin_metrics.py
muffin_metrics-0.1.4.dist-info/DESCRIPTION.rst
muffin_metrics-0.1.4.dist-info/METADATA
muffin_metrics-0.1.4.dist-info/RECORD
muffin_metrics-0.1.4.dist-info/WHEEL
muffin_metrics-0.1.4.dist-info/metadata.json
muffin_metrics-0.1.4.dist-info/top_level.txt
