Metadata-Version: 2.0
Name: muffin-metrics
Version: 0.1.4
Summary: UNKNOWN
Home-page: https://github.com/klen/muffin-metrics
Author: Kirill Klenov
Author-email: horneds@gmail.com
License: MIT
Keywords: asyncio,aiohttp,muffin,metrics
Platform: Any
Classifier: Development Status :: 4 - Beta
Classifier: Intended Audience :: Developers
Classifier: License :: OSI Approved :: MIT License
Classifier: Natural Language :: English
Classifier: Natural Language :: Russian
Classifier: Operating System :: OS Independent
Classifier: Programming Language :: Python :: 3
Classifier: Programming Language :: Python
Classifier: Topic :: Software Development :: Libraries :: Python Modules
Classifier: Topic :: Software Development :: Testing
Classifier: Topic :: Utilities
Requires-Dist: muffin (>=0.0.99)
